odoo/addons/rma_procurement_customer/README.rst
odoo/addons/rma_procurement_customer/__init__.py
odoo/addons/rma_procurement_customer/__manifest__.py
odoo/addons/rma_procurement_customer/i18n/it.po
odoo/addons/rma_procurement_customer/i18n/rma_procurement_customer.pot
odoo/addons/rma_procurement_customer/models/__init__.py
odoo/addons/rma_procurement_customer/models/rma.py
odoo/addons/rma_procurement_customer/readme/CONTRIBUTORS.md
odoo/addons/rma_procurement_customer/readme/DESCRIPTION.md
odoo/addons/rma_procurement_customer/static/description/icon.png
odoo/addons/rma_procurement_customer/static/description/index.html
odoo/addons/rma_procurement_customer/tests/__init__.py
odoo/addons/rma_procurement_customer/tests/test_rma_procurement_customer.py
odoo/addons/rma_procurement_customer/wizards/__init__.py
odoo/addons/rma_procurement_customer/wizards/stock_return_picking.py
odoo_addon_rma_procurement_customer-16.0.1.0.0.4.dist-info/METADATA
odoo_addon_rma_procurement_customer-16.0.1.0.0.4.dist-info/WHEEL
odoo_addon_rma_procurement_customer-16.0.1.0.0.4.dist-info/top_level.txt
odoo_addon_rma_procurement_customer-16.0.1.0.0.4.dist-info/RECORD
